mei/__init__.py
mei/background_helper.py
mei/domain.py
mei/import_helpers.py
mei/initial.py
mei/integration.py
mei/main.py
mei/methods.py
mei/mixins.py
mei/modules.py
mei/objectives.py
mei/optimization.py
mei/stoppers.py
mei/tracking.py
neuro_mei-0.0.0.dist-info/LICENSE
neuro_mei-0.0.0.dist-info/METADATA
neuro_mei-0.0.0.dist-info/WHEEL
neuro_mei-0.0.0.dist-info/top_level.txt
neuro_mei-0.0.0.dist-info/RECORD
