Metadata-Version: 2.1
Name: neuro-mei
Version: 0.0.0
Summary: A framework used to generate most exciting images (MEIs)
Home-page: https://github.com/sinzlab/mei
Author: Christoph Blessing
Author-email: chris24.blessing@gmail.com
License: MIT
Keywords: feature visualization MEI pytorch
Classifier: Development Status :: 3 - Alpha
Classifier: Intended Audience :: Science/Research
Classifier: Programming Language :: Python :: 3 :: Only
Classifier: License :: OSI Approved :: MIT License
Classifier: Natural Language :: English
Classifier: Topic :: Scientific/Engineering :: Bio-Informatics
License-File: LICENSE
Requires-Dist: torch >=0.4.0
Requires-Dist: scipy
Requires-Dist: numpy
Requires-Dist: torchvision
Requires-Dist: datajoint
Requires-Dist: nnfabrik
Requires-Dist: pytest
